TFNeuralNetworks/MLP.py
TFNeuralNetworks/NeuralNetwork.py
TFNeuralNetworks/RNN.py
TFNeuralNetworks/__init__.py
TFNeuralNetworks/test.py
TFNeuralNetworks-0.3.dist-info/METADATA
TFNeuralNetworks-0.3.dist-info/RECORD
TFNeuralNetworks-0.3.dist-info/WHEEL
TFNeuralNetworks-0.3.dist-info/top_level.txt
